comfyui_workflow_templates_media_api/__init__.py
comfyui_workflow_templates_media_api/templates/api_bfl_flux2_max_sofa_swap-1.webp
comfyui_workflow_templates_media_api/templates/api_bfl_flux2_max_sofa_swap-2.webp
comfyui_workflow_templates_media_api/templates/api_bfl_flux2_max_sofa_swap.json
comfyui_workflow_templates_media_api/templates/api_bfl_flux_1_kontext_max_image-1.webp
comfyui_workflow_templates_media_api/templates/api_bfl_flux_1_kontext_max_image-2.webp
comfyui_workflow_templates_media_api/templates/api_bfl_flux_1_kontext_max_image.json
comfyui_workflow_templates_media_api/templates/api_bfl_flux_1_kontext_multiple_images_input-1.webp
comfyui_workflow_templates_media_api/templates/api_bfl_flux_1_kontext_multiple_images_input-2.webp
comfyui_workflow_templates_media_api/templates/api_bfl_flux_1_kontext_multiple_images_input.json
comfyui_workflow_templates_media_api/templates/api_bfl_flux_1_kontext_pro_image-1.webp
comfyui_workflow_templates_media_api/templates/api_bfl_flux_1_kontext_pro_image-2.webp
comfyui_workflow_templates_media_api/templates/api_bfl_flux_1_kontext_pro_image.json
comfyui_workflow_templates_media_api/templates/api_bfl_flux_pro_t2i-1.webp
comfyui_workflow_templates_media_api/templates/api_bfl_flux_pro_t2i.json
comfyui_workflow_templates_media_api/templates/api_bria_image_edit-1.webp
comfyui_workflow_templates_media_api/templates/api_bria_image_edit-2.webp
comfyui_workflow_templates_media_api/templates/api_bria_image_edit.json
comfyui_workflow_templates_media_api/templates/api_bria_image_outpainting-1.webp
comfyui_workflow_templates_media_api/templates/api_bria_image_outpainting-2.webp
comfyui_workflow_templates_media_api/templates/api_bria_image_outpainting.json
comfyui_workflow_templates_media_api/templates/api_bytedace_seedance1_5_image_to_video-1.webp
comfyui_workflow_templates_media_api/templates/api_bytedace_seedance1_5_image_to_video.json
comfyui_workflow_templates_media_api/templates/api_bytedace_seedance1_5_text_to_video-1.webp
comfyui_workflow_templates_media_api-0.3.47.dist-info/METADATA
comfyui_workflow_templates_media_api-0.3.47.dist-info/WHEEL
comfyui_workflow_templates_media_api-0.3.47.dist-info/top_level.txt
comfyui_workflow_templates_media_api-0.3.47.dist-info/RECORD
